smart_prospective_api/__init__.py
smart_prospective_api/__main__.py
smart_prospective_api/client.py
smart_prospective_api/decorators.py
smart_prospective_api/exceptions.py
smart_prospective_api/log.py
smart_prospective_api/network.py
smart_prospective_api/string.py
smart_prospective_api-1.3.0.dist-info/METADATA
smart_prospective_api-1.3.0.dist-info/WHEEL
smart_prospective_api-1.3.0.dist-info/top_level.txt
smart_prospective_api-1.3.0.dist-info/RECORD
