Metadata-Version: 2.1
Name: smart-prospective-api
Version: 1.3.0
Summary: The Official Python client for Smart Prospective API
Home-page: https://github.com/smart-prospective/smart-prospective-api
Author: Smart Prospective
Author-email: dev@smartprospective.com
License: MIT
Platform: UNKNOWN
Requires-Dist: requests
